dlpx/__init__.py
dlpx/virtualization/__init__.py
dvp-5.0.1.dist-info/LICENSE
dvp-5.0.1.dist-info/METADATA
dvp-5.0.1.dist-info/WHEEL
dvp-5.0.1.dist-info/top_level.txt
dvp-5.0.1.dist-info/RECORD
