Metadata-Version: 2.1
Name: dvp
Version: 5.0.1
Summary: Delphix Virtualization Platform SDK
Home-page: https://developer.delphix.com
Author: Delphix
Author-email: virtualization-plugins@delphix.com
Keywords: virtualization plugin
Classifier: Development Status :: 5 - Production/Stable
Classifier: Programming Language :: Python
Classifier: Programming Language :: Python :: 3.11
Classifier: License :: OSI Approved :: Apache Software License
Classifier: Operating System :: OS Independent
Requires-Python: >=3.11, <3.12
License-File: LICENSE
Requires-Dist: dvp-common==5.0.1
Requires-Dist: dvp-libs==5.0.1
Requires-Dist: dvp-platform==5.0.1
Requires-Dist: dvp-tools==5.0.1
